{
  "images": [
    {
      "enddate": "20221001",
      "url": "https://www.bing.com/th?id=OHR.NBP_FR-FR2587277972_UHD.jpg",
      "copyright": "\"Bouquet of tulips\" de Jeff Koons, Paris (© Kiran Ridley/Stringer/getty images)",
      "copyrightlink": "/search?q=nuit+blanche&form=hpcapt&filters=HpDate%3a%2220220930_2200%22"
    },
    {
      "enddate": "20221002",
      "url": "https://www.bing.com/th?id=OHR.LotsOBalloons_FR-FR7710193255_UHD.jpg",
      "copyright": "Montgolfières pour le festival international de montgolfières d’Albuquerque, Nouveau-Mexique, États-Unis (© gmeland/Shutterstock)",
      "copyrightlink": "/search?q=montgolfi%c3%a8re&form=hpcapt&filters=HpDate%3a%2220221001_2200%22"
    },
    {
      "enddate": "20221003",
      "url": "https://www.bing.com/th?id=OHR.Porthuis_FR-FR7903021972_UHD.jpg",
      "copyright": "La capitainerie du port d’Anvers par Zaha Hadid Architects, Anvers, Belgique (© Dmitry Rukhlenko/Alamy)",
      "copyrightlink": "/search?q=anvers&form=hpcapt&filters=HpDate%3a%2220221002_2200%22"
    },
    {
      "enddate": "20221004",
      "url": "https://www.bing.com/th?id=OHR.CosmicCliffs_FR-FR8018346716_UHD.jpg",
      "copyright": "Falaises cosmiques dans la nébuleuse de la Carène (© NASA, ESA, CSA, and STScI)",
      "copyrightlink": "/search?q=semaine+mondiale+de+l%27espace&form=hpcapt&filters=HpDate%3a%2220221003_2200%22"
    },
    {
      "enddate": "20221005",
      "url": "https://www.bing.com/th?id=OHR.FlamingoTeacher_FR-FR8136863620_UHD.jpg",
      "copyright": "Flamants des Caraïbes dans la réserve de biosphère de Ría Lagartos, péninsule du Yucatán, Mexique (© Claudio Contreras/Minden Pictures)",
      "copyrightlink": "/search?q=enseignants&form=hpcapt&filters=HpDate%3a%2220221004_2200%22"
    },
    {
      "enddate": "20221006",
      "url": "https://www.bing.com/th?id=OHR.BayofBiscay_FR-FR8268857098_UHD.jpg",
      "copyright": "Baie de Gascogne dans le géoparc de la côte basque près de Bilbao, Espagne (© Olimpio Fantuz/eStock Photo)",
      "copyrightlink": "/search?q=g%c3%a9oparc+de+la+c%c3%b4te+basque&form=hpcapt&filters=HpDate%3a%2220221005_2200%22"
    },
    {
      "enddate": "20221007",
      "url": "https://www.bing.com/th?id=OHR.OberbaumBridge_FR-FR7094546471_UHD.jpg",
      "copyright": "Le pont de l’Oberbaum illuminé pendant le festival des lumières de Berlin (Festival of Lights), (© John MacDougall/AFP via Getty Images)",
      "copyrightlink": "/search?q=Festival+of+Lights+in+Berlin&FORM=hpcapt&filters=HpDate%3a%2220221006_2200%22"
    },
    {
      "enddate": "20221008",
      "url": "https://www.bing.com/th?id=OHR.GlassOctopus_FR-FR7225044238_UHD.jpg",
      "copyright": "Pieuvre transparente dans l’océan Atlantique au large du Cap Vert (© Solvin Zankl/Minden Pictures)",
      "copyrightlink": "/search?q=pieuvre&form=hpcapt&filters=HpDate%3a%2220221007_2200%22"
    },
    {
      "enddate": "20221009",
      "url": "https://www.bing.com/th?id=OHR.ChukchiSea_FR-FR7352200450_UHD.jpg",
      "copyright": "Phytoplancton dans la mer des Tchoutches au large de la côte de l’Alaska, États-Unis (© Norman Kuring/Kathryn Hansen/U.S. Geological Survey/NASA)",
      "copyrightlink": "/search?q=phytoplancton&form=hpcapt&filters=HpDate%3a%2220221008_2200%22"
    },
    {
      "enddate": "20221010",
      "url": "https://www.bing.com/th?id=OHR.ParisFall_FR-FR9840276975_UHD.jpg",
      "copyright": "Vue aérienne de Paris en automne (© encrier/iStock/Getty Images Plus)",
      "copyrightlink": "/search?q=Paris&form=hpcapt&filters=HpDate%3a%2220221009_2200%22"
    },
    {
      "enddate": "20221011",
      "url": "https://www.bing.com/th?id=OHR.ArbresOcres_FR-FR0003744985_UHD.jpg",
      "copyright": "Cyprès chauves aux couleurs d’automne en Isère (© Jean-Philippe Delobelle/Minden Images)",
      "copyrightlink": "/search?q=cypr%c3%a8s+chauve&form=hpcapt&filters=HpDate%3a%2220221010_2200%22"
    },
    {
      "enddate": "20221012",
      "url": "https://www.bing.com/th?id=OHR.AmmoniteGraveyard_FR-FR7475989141_UHD.jpg",
      "copyright": "Sol d'ammonite près de Monmouth Beach, côte jurassique, patrimoine mondial de l’UNESCO, Dorset, Angleterre (© AWL Images/Danita Delimont)",
      "copyrightlink": "/search?q=dorset+angleterre&form=hpcapt&filters=HpDate%3a%2220221011_2200%22"
    },
    {
      "enddate": "20221013",
      "url": "https://www.bing.com/th?id=OHR.AlaskaMoose_FR-FR7605612765_UHD.jpg",
      "copyright": "Élans mâle et femelle dans le parc national du Denali, Alaska, États-Unis (© Yva Momatiuk and John Eastcott/Minden Pictures)",
      "copyrightlink": "/search?q=%c3%a9lan&form=hpcapt&filters=HpDate%3a%2220221012_2200%22"
    },
    {
      "enddate": "20221014",
      "url": "https://www.bing.com/th?id=OHR.RioArazas_FR-FR7737403715_UHD.jpg",
      "copyright": "Cascade dans le parc national d'Ordesa et du Mont-Perdu, Pyrénées, Espagne (© David Santiago Garcia/Cavan Images)",
      "copyrightlink": "/search?q=pyr%c3%a9n%c3%a9es&form=hpcapt&filters=HpDate%3a%2220221013_2200%22"
    },
    {
      "enddate": "20221015",
      "url": "https://www.bing.com/th?id=OHR.NaqsheRustam_FR-FR7870768659_UHD.jpg",
      "copyright": "Le site archéologique de Naqsh-e Rustam près de Persépolis, Iran (© mshirani/Shutterstock)",
      "copyrightlink": "/search?q=Naqsh-e+Rustam&form=hpcapt&filters=HpDate%3a%2220221014_2200%22"
    },
    {
      "enddate": "20221016",
      "url": "https://www.bing.com/th?id=OHR.PrinceChristianSound_FR-FR8012906395_UHD.jpg",
      "copyright": "Passage du prince Christian dans le sud du Groenland (© Posnov/Getty Images)",
      "copyrightlink": "/search?q=Passage+du+prince+Christian&form=hpcapt&filters=HpDate%3a%2220221015_2200%22"
    },
    {
      "enddate": "20221017",
      "url": "https://www.bing.com/th?id=OHR.SwedenOwl_FR-FR8158494259_UHD.jpg",
      "copyright": "Hibou moyen-duc dans les monts de Bohême-Moravie en République Tchèque (© Ondrej Prosicky/Alamy)",
      "copyrightlink": "/search?q=hibou+moyen-duc&form=hpcapt&filters=HpDate%3a%2220221016_2200%22"
    },
    {
      "enddate": "20221018",
      "url": "https://www.bing.com/th?id=OHR.GB25Anni_FR-FR8300457123_UHD.jpg",
      "copyright": "Musée Guggenheim de Bilbao, Espagne (© Jeremy Horner/Getty Images)",
      "copyrightlink": "/search?q=bilbao&form=hpcapt&filters=HpDate%3a%2220221017_2200%22"
    },
    {
      "enddate": "20221019",
      "url": "https://www.bing.com/th?id=OHR.WartburgCastle_FR-FR8419207740_UHD.jpg",
      "copyright": "Forêt de Thuringe en automne et le château de la Wartbourg, Allemagne (© ezypix/Getty Images)",
      "copyrightlink": "/search?q=For%c3%aat+de+Thuringe&form=hpcapt&filters=HpDate%3a%2220221018_2200%22"
    },
    {
      "enddate": "20221020",
      "url": "https://www.bing.com/th?id=OHR.SlothDay_FR-FR8549168317_UHD.jpg",
      "copyright": "Maman paresseux d’Hoffmann et son petit, Puerto Viejo de Talamanca, Costa Rica (© Suzi Eszterhas/Minden Pictures)",
      "copyrightlink": "/search?q=L%27unau+d%27Hoffmann&form=hpcapt&filters=HpDate%3a%2220221019_2200%22"
    },
    {
      "enddate": "20221021",
      "url": "https://www.bing.com/th?id=OHR.LacSinclair_FR-FR0616776159_UHD.jpg",
      "copyright": "Le lac à l’Anglais et les fausses ruines d’une chapelle à Chamonix (© Aishe/Shutterstock)",
      "copyrightlink": "/search?q=lac+%c3%a0+l%27anglais+chamonix&form=hpcapt&filters=HpDate%3a%2220221020_2200%22"
    },
    {
      "enddate": "20221022",
      "url": "https://www.bing.com/th?id=OHR.KarstMountains_FR-FR0753680541_UHD.jpg",
      "copyright": "Montagnes de karst près de Guilin and et le parc national du fleuve Lijiang, Chine (© Sean Pavone/Alamy)",
      "copyrightlink": "/search?q=Guilin+chine&form=hpcapt&filters=HpDate%3a%2220221021_2200%22"
    },
    {
      "enddate": "20221023",
      "url": "https://www.bing.com/th?id=OHR.Knobbelzwaan_FR-FR0893259980_UHD.jpg",
      "copyright": "Cygne muet dans la réserve naturelle Valkenhorst, près de Valkenswaard, Pays-Bas (© David Pattyn/Minden Pictures)",
      "copyrightlink": "/search?q=cygne+muet&form=hpcapt&filters=HpDate%3a%2220221022_2200%22"
    },
    {
      "enddate": "20221024",
      "url": "https://www.bing.com/th?id=OHR.GuwahatiDiwali_FR-FR0155331503_UHD.jpg",
      "copyright": "Lampes à huile sur un rangoli pour célébrer Diwali à Guwahati (© Biju Boro/Getty Images)",
      "copyrightlink": "/search?q=diwali+f%c3%aate+des+lumi%c3%a8res&form=hpcapt&filters=HpDate%3a%2220221023_2200%22"
    },
    {
      "enddate": "20221025",
      "url": "https://www.bing.com/th?id=OHR.OrcusMouth_FR-FR1196570003_UHD.jpg",
      "copyright": "La bouche d’Orcus dans les Jardins de Bomarzo à Bomarzo, Italie (© Scott Wilson/Alamy)",
      "copyrightlink": "/search?q=Bomarzo&form=hpcapt&filters=HpDate%3a%2220221024_2200%22"
    },
    {
      "enddate": "20221026",
      "url": "https://www.bing.com/th?id=OHR.BrockenSpecter_FR-FR1408040117_UHD.jpg",
      "copyright": "Spectre de Brocken dans le Parc national du Balkan central, Bulgarie (© Maya Karkalicheva/Getty Images)",
      "copyrightlink": "/search?q=spectre+de+brocken&form=hpcapt&filters=HpDate%3a%2220221025_2200%22"
    },
    {
      "enddate": "20221027",
      "url": "https://www.bing.com/th?id=OHR.BridgeofSighs_FR-FR1544703204_UHD.jpg",
      "copyright": "Le pont des Soupirs à Venise, Italie (© Doug Pearson/Alamy)",
      "copyrightlink": "/search?q=pont+des+soupirs&form=hpcapt&filters=HpDate%3a%2220221026_2200%22"
    },
    {
      "enddate": "20221028",
      "url": "https://www.bing.com/th?id=OHR.ChocolateFair_FR-FR1725780390_UHD.jpg",
      "copyright": "Différents types de chocolats dans une vitrine (© Ivan/Getty Images)",
      "copyrightlink": "/search?q=salon+du+chocolat+paris&form=hpcapt&filters=HpDate%3a%2220221027_2200%22"
    },
    {
      "enddate": "20221029",
      "url": "https://www.bing.com/th?id=OHR.SeaAngel_FR-FR5791750033_UHD.jpg",
      "copyright": "Ange de mer (© Alexander Semenov Images/Shutterstock)",
      "copyrightlink": "/search?q=Gymnosomata&form=hpcapt&filters=HpDate%3a%2220221028_2200%22"
    },
    {
      "enddate": "20221030",
      "url": "https://www.bing.com/th?id=OHR.SealRiver_FR-FR1987672591_UHD.jpg",
      "copyright": "Ours polaire dans la baie d’Hudson, Manitoba, Canada (© Sean Crane/Minden Pictures)",
      "copyrightlink": "/search?q=ours+blanc&form=hpcapt&filters=HpDate%3a%2220221029_2200%22"
    },
    {
      "enddate": "20221031",
      "url": "https://www.bing.com/th?id=OHR.WychwoodForest_FR-FR2398175122_UHD.jpg",
      "copyright": "La forêt de Wychwood près de Chipping Norton, Oxfordshire, Angleterre (© Frederick Ardley/Getty Images)",
      "copyrightlink": "/search?q=halloween&form=hpcapt&filters=HpDate%3a%2220221030_2300%22"
    }
  ],
  "months": {
    "archive": [
      "202210"
    ],
    "active": []
  }
}